<?xml version="1.0" encoding="UTF-8"?>


<Patch>
	<Operation Class="PatchOperationAdd">
		<xpath>Defs/rjw.HediffDef_PartBase[defName="Breasts"]</xpath>
		<value>
			<comps>
				<li Class="RJW_Menstruation.CompProperties_Breast">
					<BreastTex>Breasts/Breast</BreastTex>
					<BlacknippleColor>(55,20,0)</BlacknippleColor>
				</li>
			</comps>
		</value>
	</Operation>
	
	<Operation Class="PatchOperationAdd">
		<xpath>Defs/rjw.HediffDef_PartBase[defName="SlimeBreasts"]</xpath>
		<value>
			<comps>
				<li Class="RJW_Menstruation.CompProperties_Breast">
					<BreastTex>Breasts/Breast</BreastTex>
					<BlacknippleColor>(55,20,0)</BlacknippleColor>
				</li>
			</comps>
		</value>
	</Operation>
	
</Patch>